pygameshort/__init__.py
pygameshort-1.0.2.dist-info/METADATA
pygameshort-1.0.2.dist-info/WHEEL
pygameshort-1.0.2.dist-info/top_level.txt
pygameshort-1.0.2.dist-info/RECORD
