Metadata-Version: 2.2
Name: pygameshort
Version: 1.0.2
Summary: A UI extention onto pygame. Quite simple actually.
Home-page: 
Author: Neo Zetterberg
Author-email: 20091103neo@gmail.com
Classifier: Programming Language :: Python :: 3
Classifier: Operating System :: OS Independent
Requires-Python: >=3.7
Requires-Dist: secure_network
Requires-Dist: pygame
Requires-Dist: pyperclip
Dynamic: author
Dynamic: author-email
Dynamic: classifier
Dynamic: description
Dynamic: description-content-type
Dynamic: requires-dist
Dynamic: requires-python
Dynamic: summary
